tests/__init__.py
tests/tweesky/__init__.py
tests/tweesky/test_main.py
tests/tweesky/parser/__init__.py
tests/tweesky/parser/test_html_parser.py
tests/tweesky/parser/test_spotify_parser.py
tweesky/__init__.py
tweesky/config.py
tweesky/main.py
tweesky/model/__init__.py
tweesky/model/card.py
tweesky/output/__init__.py
tweesky/output/html/__init__.py
tweesky/output/html/html_output.py
tweesky/output/json/__init__.py
tweesky/output/json/json_output.py
tweesky/parser/__init__.py
tweesky/parser/html_parser.py
tweesky/parser/parser_factory.py
tweesky/parser/spotify_parser.py
tweesky-0.0.6.dist-info/LICENSE
tweesky-0.0.6.dist-info/METADATA
tweesky-0.0.6.dist-info/WHEEL
tweesky-0.0.6.dist-info/top_level.txt
tweesky-0.0.6.dist-info/RECORD
