Metadata-Version: 2.1
Name: tweesky
Version: 0.0.6
Summary: Grab OpenGraph and Twitter Cards metadata from URLs, HTML documents and Spotify links
Home-page: https://github.com/gcatanese/Tweesky
Author: Beppe Catanese
License: Apache-2.0
Keywords: OpenGraph,TwitterCards,Social Media,Spotify
Classifier: Programming Language :: Python :: 3
Classifier: License :: OSI Approved :: Apache Software License
Classifier: Operating System :: OS Independent
Classifier: Intended Audience :: Developers
Classifier: Topic :: Software Development :: Libraries :: Python Modules
License-File: LICENSE
